{
  "timestamp": "2025-12-07T17:14:33.972Z",
  "brand": "Tesla",
  "suggestion": {
    "id": "1",
    "title": "Reassure on Production & Delivery",
    "rationale": "Production & delivery has 81 mentions with high intensity (25) and 62% positive sentiment; a promotional tweet can address concerns and highlight progress to boost positivity.",
    "topic": "production & delivery",
    "priority": "high",
    "suggested_copy": "Production hitting high gear! More Teslas rolling out every day. Check your app for updates 🚀 https://t.co/deliveries",
    "tone": "promotional"
  },
  "ads": [
    {
      "campaign": {
        "name": "[GrokAds] Production hitting high gear!",
        "daily_budget_micros": 1000000,
        "objective": "AWARENESS",
        "entity_status": "PAUSED"
      },
      "line_item": {
        "name": "Targeting: Tesla production EV production",
        "product_type": "PROMOTED_TWEETS",
        "placements": [
          "ALL_ON_TWITTER"
        ],
        "objective": "AWARENESS",
        "bid_strategy": "AUTO",
        "bid_amount_micros": null,
        "entity_status": "PAUSED",
        "targeting_criteria": {
          "keywords": [
            "Tesla production",
            "EV production",
            "Tesla factory"
          ],
          "interests": [
            "Tesla",
            "Electric vehicles",
            "Automotive"
          ]
        }
      },
      "creative": {
        "headline": "Production hitting high gear!",
        "body": "More Teslas rolling out every day 🚀",
        "media_url": "https://imgen.x.ai/xai-imgen/xai-tmp-imgen-4276f0c2-a00e-4412-a085-fb18907767bd.png",
        "prompt_used": "Photorealistic cinematic high-fidelity macro close-up product shot with high detail of a sleek shiny new Tesla Model Y front grille and headlights on the production line, dramatic low-key lighting, cool-toned color palette of blues and purples, minimalist design with clean composition and negative space, moody serene atmosphere, hero Tesla car occupying 60% of frame, subtle blurred background reflecting production conveyor elements, reflective glossy surfaces"
      }
    },
    {
      "campaign": {
        "name": "[GrokAds] Deliveries ramping up!",
        "daily_budget_micros": 1000000,
        "objective": "TWEET_ENGAGEMENTS",
        "entity_status": "PAUSED"
      },
      "line_item": {
        "name": "Targeting: Tesla delivery Tesla order",
        "product_type": "PROMOTED_TWEETS",
        "placements": [
          "ALL_ON_TWITTER"
        ],
        "objective": "TWEET_ENGAGEMENTS",
        "bid_strategy": "MAX",
        "bid_amount_micros": 500000,
        "entity_status": "PAUSED",
        "targeting_criteria": {
          "keywords": [
            "Tesla delivery",
            "Tesla order",
            "EV delivery"
          ],
          "interests": [
            "Tesla owners",
            "Electric cars",
            "Car delivery"
          ]
        }
      },
      "creative": {
        "headline": "Deliveries ramping up!",
        "body": "Your Tesla is on the way. Sync now 🚀",
        "media_url": "https://imgen.x.ai/xai-imgen/xai-tmp-imgen-b98fb28f-f928-4f17-99e3-ede6ee7fcea9.png",
        "prompt_used": "Photorealistic cinematic high-fidelity wide environmental lifestyle shot of a row of sleek modern Tesla cars in a delivery lot at urban night, dramatic lighting with muted dark blues and warm yellows, reflective wet street creating sophisticated futuristic atmosphere, minimalist design, moody scene, hero Tesla cars as clear focal point occupying 60% of frame, subtle blurred background with delivery center vibes and open road hint"
      }
    }
  ]
}